{
	"name": "SourceDataset_j3v",
	"properties": {
		"linkedServiceName": {
			"referenceName": "lego_http",
			"type": "LinkedServiceReference"
		},
		"annotations": [],
		"type": "DelimitedText",
		"typeProperties": {
			"location": {
				"type": "HttpServerLocation",
				"relativeUrl": "themes.csv.gz"
			},
			"columnDelimiter": ",",
			"compressionCodec": "gzip",
			"escapeChar": "\\",
			"firstRowAsHeader": true,
			"quoteChar": "\""
		},
		"schema": [
			{
				"name": "id",
				"type": "String"
			},
			{
				"name": "name",
				"type": "String"
			},
			{
				"name": "parent_id",
				"type": "String"
			}
		]
	},
	"type": "Microsoft.DataFactory/factories/datasets"
}